MongoRandomizer/__init__.py
MongoRandomizer-0.3.11.dist-info/METADATA
MongoRandomizer-0.3.11.dist-info/RECORD
MongoRandomizer-0.3.11.dist-info/WHEEL
MongoRandomizer-0.3.11.dist-info/entry_points.txt
MongoRandomizer-0.3.11.dist-info/top_level.txt
