Metadata-Version: 2.1
Name: MongoRandomizer
Version: 0.3.11
Summary: A small and basic package to create randomized MongoDB documents and trivial load.
Home-page: https://github.com/graboskyc/MongoDataRandomizer
Author: graboskyc
Author-email: chris@grabosky.net
License: UNKNOWN
Platform: UNKNOWN
Requires-Dist: ConfigParser
Requires-Dist: pymongo
Requires-Dist: faker
Requires-Dist: multiprocessing
Requires-Dist: dnspython
